uriregistry/__init__.py
uriregistry/models.py
uriregistry/registry.py
uriregistry/utils.py
uriregistry/views.py
uriregistry-0.4.0.dist-info/METADATA
uriregistry-0.4.0.dist-info/WHEEL
uriregistry-0.4.0.dist-info/entry_points.txt
uriregistry-0.4.0.dist-info/licenses/LICENSE
uriregistry-0.4.0.dist-info/RECORD
